MANIFEST.in
RELEASE-VERSION
get_git_version.py
setup.py
maried.egg-info/PKG-INFO
maried.egg-info/SOURCES.txt
maried.egg-info/dependency_links.txt
maried.egg-info/not-zip-safe
maried.egg-info/requires.txt
maried.egg-info/top_level.txt
src/__init__.py
src/core.py
src/gstreamer.py
src/joyceRS.py
src/lastfm.py
src/maint.py
src/mongo.py