Metadata-Version: 1.0
Name: maried
Version: 0.1.0a2
Summary: MarieD music daemon
Home-page: http://github.com/bwesterb/maried/
Author: Bas Westerbaan
Author-email: bas@westerbaan.name
License: UNKNOWN
Platform: UNKNOWN
